{
  "url": "http://scoot.net/gallery/2006/01/bigwetone/",
  "slug": "2006/01/bigwetone",
  "title": "The Big Wet One",
  "year": 2006,
  "month": 1,
  "date_rally": "2006-01",
  "photo_count": 268,
  "stories": [],
  "description": "The Big Wet One was a scooter rally held in cold weather. It featured scooter enthusiasts riding and socializing despite the winter conditions.",
  "city": "null",
  "country": "US",
  "recurring": false,
  "notable_facts": [
    "held in January 2006",
    "part of scoot.net's gallery"
  ],
  "related_clubs": [],
  "source_confidence": "low",
  "enriched": true,
  "enriched_at": "2026-03-15T00:55:05Z",
  "enriched_provider": "Cerebras"
}