[
  {
    "pic_id": "372262",
    "pic_url": "http://scoot.net/gallery/pic.html?pic=372262&b=2009/06/rally9fromouterspace/Shannon/tinyindex.html",
    "photographer": "Shannon",
    "date_rally": "2009-06",
    "date_exif": "2009:06:13 22:32:37",
    "date_canonical": null,
    "date_source": "rally_slug",
    "r2_thumb": "https://pub-298bb0f2fc0a4462bd54d403b1bddbca.r2.dev/gallery/200906-Shannon/372262/thumb.jpg",
    "r2_full": null,
    "exif_meta": {
      "DateTimeOriginal": "2009:06:13 22:32:37",
      "Make": "Canon",
      "Model": "Canon PowerShot SD1100 IS",
      "_warning": "Camera clock accuracy not guaranteed. Use date_canonical for trusted dates."
    }
  },
  {
    "pic_id": "372263",
    "pic_url": "http://scoot.net/gallery/pic.html?pic=372263&b=2009/06/rally9fromouterspace/Shannon/tinyindex.html",
    "photographer": "Shannon",
    "date_rally": "2009-06",
    "date_exif": "2009:06:14 10:38:26",
    "date_canonical": null,
    "date_source": "rally_slug",
    "r2_thumb": "https://pub-298bb0f2fc0a4462bd54d403b1bddbca.r2.dev/gallery/200906-Shannon/372263/thumb.jpg",
    "r2_full": null,
    "exif_meta": {
      "DateTimeOriginal": "2009:06:14 10:38:26",
      "Make": "Canon",
      "Model": "Canon PowerShot SD1100 IS",
      "_warning": "Camera clock accuracy not guaranteed. Use date_canonical for trusted dates."
    }
  },
  {
    "pic_id": "372264",
    "pic_url": "http://scoot.net/gallery/pic.html?pic=372264&b=2009/06/rally9fromouterspace/Shannon/tinyindex.html",
    "photographer": "Shannon",
    "date_rally": "2009-06",
    "date_exif": "2009:06:14 10:38:38",
    "date_canonical": null,
    "date_source": "rally_slug",
    "r2_thumb": "https://pub-298bb0f2fc0a4462bd54d403b1bddbca.r2.dev/gallery/200906-Shannon/372264/thumb.jpg",
    "r2_full": null,
    "exif_meta": {
      "DateTimeOriginal": "2009:06:14 10:38:38",
      "Make": "Canon",
      "Model": "Canon PowerShot SD1100 IS",
      "_warning": "Camera clock accuracy not guaranteed. Use date_canonical for trusted dates."
    }
  },
  {
    "pic_id": "372265",
    "pic_url": "http://scoot.net/gallery/pic.html?pic=372265&b=2009/06/rally9fromouterspace/Shannon/tinyindex.html",
    "photographer": "Shannon",
    "date_rally": "2009-06",
    "date_exif": "2009:06:14 10:40:40",
    "date_canonical": null,
    "date_source": "rally_slug",
    "r2_thumb": "https://pub-298bb0f2fc0a4462bd54d403b1bddbca.r2.dev/gallery/200906-Shannon/372265/thumb.jpg",
    "r2_full": null,
    "exif_meta": {
      "DateTimeOriginal": "2009:06:14 10:40:40",
      "Make": "Canon",
      "Model": "Canon PowerShot SD1100 IS",
      "_warning": "Camera clock accuracy not guaranteed. Use date_canonical for trusted dates."
    }
  },
  {
    "pic_id": "372266",
    "pic_url": "http://scoot.net/gallery/pic.html?pic=372266&b=2009/06/rally9fromouterspace/Shannon/tinyindex.html",
    "photographer": "Shannon",
    "date_rally": "2009-06",
    "date_exif": "2009:06:14 10:43:28",
    "date_canonical": null,
    "date_source": "rally_slug",
    "r2_thumb": "https://pub-298bb0f2fc0a4462bd54d403b1bddbca.r2.dev/gallery/200906-Shannon/372266/thumb.jpg",
    "r2_full": null,
    "exif_meta": {
      "DateTimeOriginal": "2009:06:14 10:43:28",
      "Make": "Canon",
      "Model": "Canon PowerShot SD1100 IS",
      "_warning": "Camera clock accuracy not guaranteed. Use date_canonical for trusted dates."
    }
  },
  {
    "pic_id": "372267",
    "pic_url": "http://scoot.net/gallery/pic.html?pic=372267&b=2009/06/rally9fromouterspace/Shannon/tinyindex.html",
    "photographer": "Shannon",
    "date_rally": "2009-06",
    "date_exif": "2009:06:14 10:44:52",
    "date_canonical": null,
    "date_source": "rally_slug",
    "r2_thumb": "https://pub-298bb0f2fc0a4462bd54d403b1bddbca.r2.dev/gallery/200906-Shannon/372267/thumb.jpg",
    "r2_full": null,
    "exif_meta": {
      "DateTimeOriginal": "2009:06:14 10:44:52",
      "Make": "Canon",
      "Model": "Canon PowerShot SD1100 IS",
      "_warning": "Camera clock accuracy not guaranteed. Use date_canonical for trusted dates."
    }
  },
  {
    "pic_id": "372268",
    "pic_url": "http://scoot.net/gallery/pic.html?pic=372268&b=2009/06/rally9fromouterspace/Shannon/tinyindex.html",
    "photographer": "Shannon",
    "date_rally": "2009-06",
    "date_exif": "2009:06:14 10:45:02",
    "date_canonical": null,
    "date_source": "rally_slug",
    "r2_thumb": "https://pub-298bb0f2fc0a4462bd54d403b1bddbca.r2.dev/gallery/200906-Shannon/372268/thumb.jpg",
    "r2_full": null,
    "exif_meta": {
      "DateTimeOriginal": "2009:06:14 10:45:02",
      "Make": "Canon",
      "Model": "Canon PowerShot SD1100 IS",
      "_warning": "Camera clock accuracy not guaranteed. Use date_canonical for trusted dates."
    }
  },
  {
    "pic_id": "372269",
    "pic_url": "http://scoot.net/gallery/pic.html?pic=372269&b=2009/06/rally9fromouterspace/Shannon/tinyindex.html",
    "photographer": "Shannon",
    "date_rally": "2009-06",
    "date_exif": "2009:06:14 10:45:11",
    "date_canonical": null,
    "date_source": "rally_slug",
    "r2_thumb": "https://pub-298bb0f2fc0a4462bd54d403b1bddbca.r2.dev/gallery/200906-Shannon/372269/thumb.jpg",
    "r2_full": null,
    "exif_meta": {
      "DateTimeOriginal": "2009:06:14 10:45:11",
      "Make": "Canon",
      "Model": "Canon PowerShot SD1100 IS",
      "_warning": "Camera clock accuracy not guaranteed. Use date_canonical for trusted dates."
    }
  },
  {
    "pic_id": "372270",
    "pic_url": "http://scoot.net/gallery/pic.html?pic=372270&b=2009/06/rally9fromouterspace/Shannon/tinyindex.html",
    "photographer": "Shannon",
    "date_rally": "2009-06",
    "date_exif": "2009:06:14 11:09:51",
    "date_canonical": null,
    "date_source": "rally_slug",
    "r2_thumb": "https://pub-298bb0f2fc0a4462bd54d403b1bddbca.r2.dev/gallery/200906-Shannon/372270/thumb.jpg",
    "r2_full": null,
    "exif_meta": {
      "DateTimeOriginal": "2009:06:14 11:09:51",
      "Make": "Canon",
      "Model": "Canon PowerShot SD1100 IS",
      "_warning": "Camera clock accuracy not guaranteed. Use date_canonical for trusted dates."
    }
  },
  {
    "pic_id": "372271",
    "pic_url": "http://scoot.net/gallery/pic.html?pic=372271&b=2009/06/rally9fromouterspace/Shannon/tinyindex.html",
    "photographer": "Shannon",
    "date_rally": "2009-06",
    "date_exif": "2009:06:14 11:10:04",
    "date_canonical": null,
    "date_source": "rally_slug",
    "r2_thumb": "https://pub-298bb0f2fc0a4462bd54d403b1bddbca.r2.dev/gallery/200906-Shannon/372271/thumb.jpg",
    "r2_full": null,
    "exif_meta": {
      "DateTimeOriginal": "2009:06:14 11:10:04",
      "Make": "Canon",
      "Model": "Canon PowerShot SD1100 IS",
      "_warning": "Camera clock accuracy not guaranteed. Use date_canonical for trusted dates."
    }
  },
  {
    "pic_id": "372272",
    "pic_url": "http://scoot.net/gallery/pic.html?pic=372272&b=2009/06/rally9fromouterspace/Shannon/tinyindex.html",
    "photographer": "Shannon",
    "date_rally": "2009-06",
    "date_exif": "2009:06:14 11:51:11",
    "date_canonical": null,
    "date_source": "rally_slug",
    "r2_thumb": "https://pub-298bb0f2fc0a4462bd54d403b1bddbca.r2.dev/gallery/200906-Shannon/372272/thumb.jpg",
    "r2_full": null,
    "exif_meta": {
      "DateTimeOriginal": "2009:06:14 11:51:11",
      "Make": "Canon",
      "Model": "Canon PowerShot SD1100 IS",
      "_warning": "Camera clock accuracy not guaranteed. Use date_canonical for trusted dates."
    }
  },
  {
    "pic_id": "372273",
    "pic_url": "http://scoot.net/gallery/pic.html?pic=372273&b=2009/06/rally9fromouterspace/Shannon/tinyindex.html",
    "photographer": "Shannon",
    "date_rally": "2009-06",
    "date_exif": "2009:06:14 12:04:15",
    "date_canonical": null,
    "date_source": "rally_slug",
    "r2_thumb": "https://pub-298bb0f2fc0a4462bd54d403b1bddbca.r2.dev/gallery/200906-Shannon/372273/thumb.jpg",
    "r2_full": null,
    "exif_meta": {
      "DateTimeOriginal": "2009:06:14 12:04:15",
      "Make": "Canon",
      "Model": "Canon PowerShot SD1100 IS",
      "_warning": "Camera clock accuracy not guaranteed. Use date_canonical for trusted dates."
    }
  },
  {
    "pic_id": "372274",
    "pic_url": "http://scoot.net/gallery/pic.html?pic=372274&b=2009/06/rally9fromouterspace/Shannon/tinyindex.html",
    "photographer": "Shannon",
    "date_rally": "2009-06",
    "date_exif": "2009:06:14 12:08:58",
    "date_canonical": null,
    "date_source": "rally_slug",
    "r2_thumb": "https://pub-298bb0f2fc0a4462bd54d403b1bddbca.r2.dev/gallery/200906-Shannon/372274/thumb.jpg",
    "r2_full": null,
    "exif_meta": {
      "DateTimeOriginal": "2009:06:14 12:08:58",
      "Make": "Canon",
      "Model": "Canon PowerShot SD1100 IS",
      "_warning": "Camera clock accuracy not guaranteed. Use date_canonical for trusted dates."
    }
  },
  {
    "pic_id": "374833",
    "pic_url": "http://scoot.net/gallery/pic.html?pic=374833&b=2009/06/rally9fromouterspace/Christine_Greeno/tinyindex.html",
    "photographer": "Christine_Greeno",
    "date_rally": "2009-06",
    "date_exif": "2009:06:13 08:22:55",
    "date_canonical": null,
    "date_source": "rally_slug",
    "r2_thumb": "https://pub-298bb0f2fc0a4462bd54d403b1bddbca.r2.dev/gallery/200906-Christine_Greeno/374833/thumb.jpg",
    "r2_full": null,
    "exif_meta": {
      "DateTimeOriginal": "2009:06:13 08:22:55",
      "Make": "OLYMPUS IMAGING CORP.",
      "Model": "u850SW,S850SW",
      "_warning": "Camera clock accuracy not guaranteed. Use date_canonical for trusted dates."
    }
  },
  {
    "pic_id": "374834",
    "pic_url": "http://scoot.net/gallery/pic.html?pic=374834&b=2009/06/rally9fromouterspace/Christine_Greeno/tinyindex.html",
    "photographer": "Christine_Greeno",
    "date_rally": "2009-06",
    "date_exif": "2009:06:13 08:23:08",
    "date_canonical": null,
    "date_source": "rally_slug",
    "r2_thumb": "https://pub-298bb0f2fc0a4462bd54d403b1bddbca.r2.dev/gallery/200906-Christine_Greeno/374834/thumb.jpg",
    "r2_full": null,
    "exif_meta": {
      "DateTimeOriginal": "2009:06:13 08:23:08",
      "Make": "OLYMPUS IMAGING CORP.",
      "Model": "u850SW,S850SW",
      "_warning": "Camera clock accuracy not guaranteed. Use date_canonical for trusted dates."
    }
  },
  {
    "pic_id": "374835",
    "pic_url": "http://scoot.net/gallery/pic.html?pic=374835&b=2009/06/rally9fromouterspace/Christine_Greeno/tinyindex.html",
    "photographer": "Christine_Greeno",
    "date_rally": "2009-06",
    "date_exif": "2009:06:13 08:23:22",
    "date_canonical": null,
    "date_source": "rally_slug",
    "r2_thumb": "https://pub-298bb0f2fc0a4462bd54d403b1bddbca.r2.dev/gallery/200906-Christine_Greeno/374835/thumb.jpg",
    "r2_full": null,
    "exif_meta": {
      "DateTimeOriginal": "2009:06:13 08:23:22",
      "Make": "OLYMPUS IMAGING CORP.",
      "Model": "u850SW,S850SW",
      "_warning": "Camera clock accuracy not guaranteed. Use date_canonical for trusted dates."
    }
  },
  {
    "pic_id": "374836",
    "pic_url": "http://scoot.net/gallery/pic.html?pic=374836&b=2009/06/rally9fromouterspace/Christine_Greeno/tinyindex.html",
    "photographer": "Christine_Greeno",
    "date_rally": "2009-06",
    "date_exif": "2009:06:13 08:23:52",
    "date_canonical": null,
    "date_source": "rally_slug",
    "r2_thumb": "https://pub-298bb0f2fc0a4462bd54d403b1bddbca.r2.dev/gallery/200906-Christine_Greeno/374836/thumb.jpg",
    "r2_full": null,
    "exif_meta": {
      "DateTimeOriginal": "2009:06:13 08:23:52",
      "Make": "OLYMPUS IMAGING CORP.",
      "Model": "u850SW,S850SW",
      "_warning": "Camera clock accuracy not guaranteed. Use date_canonical for trusted dates."
    }
  },
  {
    "pic_id": "374837",
    "pic_url": "http://scoot.net/gallery/pic.html?pic=374837&b=2009/06/rally9fromouterspace/Christine_Greeno/tinyindex.html",
    "photographer": "Christine_Greeno",
    "date_rally": "2009-06",
    "date_exif": "2009:06:13 08:43:07",
    "date_canonical": null,
    "date_source": "rally_slug",
    "r2_thumb": "https://pub-298bb0f2fc0a4462bd54d403b1bddbca.r2.dev/gallery/200906-Christine_Greeno/374837/thumb.jpg",
    "r2_full": null,
    "exif_meta": {
      "DateTimeOriginal": "2009:06:13 08:43:07",
      "Make": "OLYMPUS IMAGING CORP.",
      "Model": "u850SW,S850SW",
      "_warning": "Camera clock accuracy not guaranteed. Use date_canonical for trusted dates."
    }
  },
  {
    "pic_id": "374838",
    "pic_url": "http://scoot.net/gallery/pic.html?pic=374838&b=2009/06/rally9fromouterspace/Christine_Greeno/tinyindex.html",
    "photographer": "Christine_Greeno",
    "date_rally": "2009-06",
    "date_exif": "2009:06:13 08:59:27",
    "date_canonical": null,
    "date_source": "rally_slug",
    "r2_thumb": "https://pub-298bb0f2fc0a4462bd54d403b1bddbca.r2.dev/gallery/200906-Christine_Greeno/374838/thumb.jpg",
    "r2_full": null,
    "exif_meta": {
      "DateTimeOriginal": "2009:06:13 08:59:27",
      "Make": "OLYMPUS IMAGING CORP.",
      "Model": "u850SW,S850SW",
      "_warning": "Camera clock accuracy not guaranteed. Use date_canonical for trusted dates."
    }
  },
  {
    "pic_id": "374839",
    "pic_url": "http://scoot.net/gallery/pic.html?pic=374839&b=2009/06/rally9fromouterspace/Christine_Greeno/tinyindex.html",
    "photographer": "Christine_Greeno",
    "date_rally": "2009-06",
    "date_exif": "2009:06:13 09:00:03",
    "date_canonical": null,
    "date_source": "rally_slug",
    "r2_thumb": "https://pub-298bb0f2fc0a4462bd54d403b1bddbca.r2.dev/gallery/200906-Christine_Greeno/374839/thumb.jpg",
    "r2_full": null,
    "exif_meta": {
      "DateTimeOriginal": "2009:06:13 09:00:03",
      "Make": "OLYMPUS IMAGING CORP.",
      "Model": "u850SW,S850SW",
      "_warning": "Camera clock accuracy not guaranteed. Use date_canonical for trusted dates."
    }
  },
  {
    "pic_id": "372231",
    "pic_url": "http://scoot.net/gallery/pic.html?pic=372231&b=2009/06/rally9fromouterspace/Angelo/tinyindex.html",
    "photographer": "Angelo",
    "date_rally": "2009-06",
    "date_exif": null,
    "date_canonical": null,
    "date_source": "rally_slug",
    "r2_thumb": "https://pub-298bb0f2fc0a4462bd54d403b1bddbca.r2.dev/gallery/200906-Angelo/372231/thumb.jpg",
    "r2_full": null,
    "exif_meta": null
  },
  {
    "pic_id": "372232",
    "pic_url": "http://scoot.net/gallery/pic.html?pic=372232&b=2009/06/rally9fromouterspace/Angelo/tinyindex.html",
    "photographer": "Angelo",
    "date_rally": "2009-06",
    "date_exif": null,
    "date_canonical": null,
    "date_source": "rally_slug",
    "r2_thumb": "https://pub-298bb0f2fc0a4462bd54d403b1bddbca.r2.dev/gallery/200906-Angelo/372232/thumb.jpg",
    "r2_full": null,
    "exif_meta": null
  },
  {
    "pic_id": "372233",
    "pic_url": "http://scoot.net/gallery/pic.html?pic=372233&b=2009/06/rally9fromouterspace/Angelo/tinyindex.html",
    "photographer": "Angelo",
    "date_rally": "2009-06",
    "date_exif": null,
    "date_canonical": null,
    "date_source": "rally_slug",
    "r2_thumb": "https://pub-298bb0f2fc0a4462bd54d403b1bddbca.r2.dev/gallery/200906-Angelo/372233/thumb.jpg",
    "r2_full": null,
    "exif_meta": null
  },
  {
    "pic_id": "372234",
    "pic_url": "http://scoot.net/gallery/pic.html?pic=372234&b=2009/06/rally9fromouterspace/Angelo/tinyindex.html",
    "photographer": "Angelo",
    "date_rally": "2009-06",
    "date_exif": null,
    "date_canonical": null,
    "date_source": "rally_slug",
    "r2_thumb": "https://pub-298bb0f2fc0a4462bd54d403b1bddbca.r2.dev/gallery/200906-Angelo/372234/thumb.jpg",
    "r2_full": null,
    "exif_meta": null
  },
  {
    "pic_id": "372235",
    "pic_url": "http://scoot.net/gallery/pic.html?pic=372235&b=2009/06/rally9fromouterspace/Angelo/tinyindex.html",
    "photographer": "Angelo",
    "date_rally": "2009-06",
    "date_exif": null,
    "date_canonical": null,
    "date_source": "rally_slug",
    "r2_thumb": "https://pub-298bb0f2fc0a4462bd54d403b1bddbca.r2.dev/gallery/200906-Angelo/372235/thumb.jpg",
    "r2_full": null,
    "exif_meta": null
  },
  {
    "pic_id": "372236",
    "pic_url": "http://scoot.net/gallery/pic.html?pic=372236&b=2009/06/rally9fromouterspace/Angelo/tinyindex.html",
    "photographer": "Angelo",
    "date_rally": "2009-06",
    "date_exif": null,
    "date_canonical": null,
    "date_source": "rally_slug",
    "r2_thumb": "https://pub-298bb0f2fc0a4462bd54d403b1bddbca.r2.dev/gallery/200906-Angelo/372236/thumb.jpg",
    "r2_full": null,
    "exif_meta": null
  },
  {
    "pic_id": "372237",
    "pic_url": "http://scoot.net/gallery/pic.html?pic=372237&b=2009/06/rally9fromouterspace/Angelo/tinyindex.html",
    "photographer": "Angelo",
    "date_rally": "2009-06",
    "date_exif": null,
    "date_canonical": null,
    "date_source": "rally_slug",
    "r2_thumb": "https://pub-298bb0f2fc0a4462bd54d403b1bddbca.r2.dev/gallery/200906-Angelo/372237/thumb.jpg",
    "r2_full": null,
    "exif_meta": null
  },
  {
    "pic_id": "372238",
    "pic_url": "http://scoot.net/gallery/pic.html?pic=372238&b=2009/06/rally9fromouterspace/Angelo/tinyindex.html",
    "photographer": "Angelo",
    "date_rally": "2009-06",
    "date_exif": null,
    "date_canonical": null,
    "date_source": "rally_slug",
    "r2_thumb": "https://pub-298bb0f2fc0a4462bd54d403b1bddbca.r2.dev/gallery/200906-Angelo/372238/thumb.jpg",
    "r2_full": null,
    "exif_meta": null
  },
  {
    "pic_id": "372239",
    "pic_url": "http://scoot.net/gallery/pic.html?pic=372239&b=2009/06/rally9fromouterspace/Angelo/tinyindex.html",
    "photographer": "Angelo",
    "date_rally": "2009-06",
    "date_exif": null,
    "date_canonical": null,
    "date_source": "rally_slug",
    "r2_thumb": "https://pub-298bb0f2fc0a4462bd54d403b1bddbca.r2.dev/gallery/200906-Angelo/372239/thumb.jpg",
    "r2_full": null,
    "exif_meta": null
  },
  {
    "pic_id": "372240",
    "pic_url": "http://scoot.net/gallery/pic.html?pic=372240&b=2009/06/rally9fromouterspace/Angelo/tinyindex.html",
    "photographer": "Angelo",
    "date_rally": "2009-06",
    "date_exif": null,
    "date_canonical": null,
    "date_source": "rally_slug",
    "r2_thumb": "https://pub-298bb0f2fc0a4462bd54d403b1bddbca.r2.dev/gallery/200906-Angelo/372240/thumb.jpg",
    "r2_full": null,
    "exif_meta": null
  },
  {
    "pic_id": "372241",
    "pic_url": "http://scoot.net/gallery/pic.html?pic=372241&b=2009/06/rally9fromouterspace/Angelo/tinyindex.html",
    "photographer": "Angelo",
    "date_rally": "2009-06",
    "date_exif": null,
    "date_canonical": null,
    "date_source": "rally_slug",
    "r2_thumb": "https://pub-298bb0f2fc0a4462bd54d403b1bddbca.r2.dev/gallery/200906-Angelo/372241/thumb.jpg",
    "r2_full": null,
    "exif_meta": null
  },
  {
    "pic_id": "372242",
    "pic_url": "http://scoot.net/gallery/pic.html?pic=372242&b=2009/06/rally9fromouterspace/Angelo/tinyindex.html",
    "photographer": "Angelo",
    "date_rally": "2009-06",
    "date_exif": null,
    "date_canonical": null,
    "date_source": "rally_slug",
    "r2_thumb": "https://pub-298bb0f2fc0a4462bd54d403b1bddbca.r2.dev/gallery/200906-Angelo/372242/thumb.jpg",
    "r2_full": null,
    "exif_meta": null
  },
  {
    "pic_id": "372243",
    "pic_url": "http://scoot.net/gallery/pic.html?pic=372243&b=2009/06/rally9fromouterspace/Angelo/tinyindex.html",
    "photographer": "Angelo",
    "date_rally": "2009-06",
    "date_exif": null,
    "date_canonical": null,
    "date_source": "rally_slug",
    "r2_thumb": "https://pub-298bb0f2fc0a4462bd54d403b1bddbca.r2.dev/gallery/200906-Angelo/372243/thumb.jpg",
    "r2_full": null,
    "exif_meta": null
  },
  {
    "pic_id": "372244",
    "pic_url": "http://scoot.net/gallery/pic.html?pic=372244&b=2009/06/rally9fromouterspace/Angelo/tinyindex.html",
    "photographer": "Angelo",
    "date_rally": "2009-06",
    "date_exif": null,
    "date_canonical": null,
    "date_source": "rally_slug",
    "r2_thumb": "https://pub-298bb0f2fc0a4462bd54d403b1bddbca.r2.dev/gallery/200906-Angelo/372244/thumb.jpg",
    "r2_full": null,
    "exif_meta": null
  },
  {
    "pic_id": "372245",
    "pic_url": "http://scoot.net/gallery/pic.html?pic=372245&b=2009/06/rally9fromouterspace/Angelo/tinyindex.html",
    "photographer": "Angelo",
    "date_rally": "2009-06",
    "date_exif": null,
    "date_canonical": null,
    "date_source": "rally_slug",
    "r2_thumb": "https://pub-298bb0f2fc0a4462bd54d403b1bddbca.r2.dev/gallery/200906-Angelo/372245/thumb.jpg",
    "r2_full": null,
    "exif_meta": null
  },
  {
    "pic_id": "372246",
    "pic_url": "http://scoot.net/gallery/pic.html?pic=372246&b=2009/06/rally9fromouterspace/Angelo/tinyindex.html",
    "photographer": "Angelo",
    "date_rally": "2009-06",
    "date_exif": null,
    "date_canonical": null,
    "date_source": "rally_slug",
    "r2_thumb": "https://pub-298bb0f2fc0a4462bd54d403b1bddbca.r2.dev/gallery/200906-Angelo/372246/thumb.jpg",
    "r2_full": null,
    "exif_meta": null
  },
  {
    "pic_id": "372247",
    "pic_url": "http://scoot.net/gallery/pic.html?pic=372247&b=2009/06/rally9fromouterspace/Angelo/tinyindex.html",
    "photographer": "Angelo",
    "date_rally": "2009-06",
    "date_exif": null,
    "date_canonical": null,
    "date_source": "rally_slug",
    "r2_thumb": "https://pub-298bb0f2fc0a4462bd54d403b1bddbca.r2.dev/gallery/200906-Angelo/372247/thumb.jpg",
    "r2_full": null,
    "exif_meta": null
  },
  {
    "pic_id": "372248",
    "pic_url": "http://scoot.net/gallery/pic.html?pic=372248&b=2009/06/rally9fromouterspace/Angelo/tinyindex.html",
    "photographer": "Angelo",
    "date_rally": "2009-06",
    "date_exif": null,
    "date_canonical": null,
    "date_source": "rally_slug",
    "r2_thumb": "https://pub-298bb0f2fc0a4462bd54d403b1bddbca.r2.dev/gallery/200906-Angelo/372248/thumb.jpg",
    "r2_full": null,
    "exif_meta": null
  },
  {
    "pic_id": "372249",
    "pic_url": "http://scoot.net/gallery/pic.html?pic=372249&b=2009/06/rally9fromouterspace/Angelo/tinyindex.html",
    "photographer": "Angelo",
    "date_rally": "2009-06",
    "date_exif": null,
    "date_canonical": null,
    "date_source": "rally_slug",
    "r2_thumb": "https://pub-298bb0f2fc0a4462bd54d403b1bddbca.r2.dev/gallery/200906-Angelo/372249/thumb.jpg",
    "r2_full": null,
    "exif_meta": null
  },
  {
    "pic_id": "372250",
    "pic_url": "http://scoot.net/gallery/pic.html?pic=372250&b=2009/06/rally9fromouterspace/Angelo/tinyindex.html",
    "photographer": "Angelo",
    "date_rally": "2009-06",
    "date_exif": null,
    "date_canonical": null,
    "date_source": "rally_slug",
    "r2_thumb": "https://pub-298bb0f2fc0a4462bd54d403b1bddbca.r2.dev/gallery/200906-Angelo/372250/thumb.jpg",
    "r2_full": null,
    "exif_meta": null
  },
  {
    "pic_id": "372251",
    "pic_url": "http://scoot.net/gallery/pic.html?pic=372251&b=2009/06/rally9fromouterspace/Angelo/tinyindex.html",
    "photographer": "Angelo",
    "date_rally": "2009-06",
    "date_exif": null,
    "date_canonical": null,
    "date_source": "rally_slug",
    "r2_thumb": "https://pub-298bb0f2fc0a4462bd54d403b1bddbca.r2.dev/gallery/200906-Angelo/372251/thumb.jpg",
    "r2_full": null,
    "exif_meta": null
  },
  {
    "pic_id": "372252",
    "pic_url": "http://scoot.net/gallery/pic.html?pic=372252&b=2009/06/rally9fromouterspace/Angelo/tinyindex.html",
    "photographer": "Angelo",
    "date_rally": "2009-06",
    "date_exif": null,
    "date_canonical": null,
    "date_source": "rally_slug",
    "r2_thumb": "https://pub-298bb0f2fc0a4462bd54d403b1bddbca.r2.dev/gallery/200906-Angelo/372252/thumb.jpg",
    "r2_full": null,
    "exif_meta": null
  },
  {
    "pic_id": "372253",
    "pic_url": "http://scoot.net/gallery/pic.html?pic=372253&b=2009/06/rally9fromouterspace/Angelo/tinyindex.html",
    "photographer": "Angelo",
    "date_rally": "2009-06",
    "date_exif": null,
    "date_canonical": null,
    "date_source": "rally_slug",
    "r2_thumb": "https://pub-298bb0f2fc0a4462bd54d403b1bddbca.r2.dev/gallery/200906-Angelo/372253/thumb.jpg",
    "r2_full": null,
    "exif_meta": null
  },
  {
    "pic_id": "372254",
    "pic_url": "http://scoot.net/gallery/pic.html?pic=372254&b=2009/06/rally9fromouterspace/Angelo/tinyindex.html",
    "photographer": "Angelo",
    "date_rally": "2009-06",
    "date_exif": null,
    "date_canonical": null,
    "date_source": "rally_slug",
    "r2_thumb": "https://pub-298bb0f2fc0a4462bd54d403b1bddbca.r2.dev/gallery/200906-Angelo/372254/thumb.jpg",
    "r2_full": null,
    "exif_meta": null
  },
  {
    "pic_id": "372255",
    "pic_url": "http://scoot.net/gallery/pic.html?pic=372255&b=2009/06/rally9fromouterspace/Angelo/tinyindex.html",
    "photographer": "Angelo",
    "date_rally": "2009-06",
    "date_exif": null,
    "date_canonical": null,
    "date_source": "rally_slug",
    "r2_thumb": "https://pub-298bb0f2fc0a4462bd54d403b1bddbca.r2.dev/gallery/200906-Angelo/372255/thumb.jpg",
    "r2_full": null,
    "exif_meta": null
  },
  {
    "pic_id": "372256",
    "pic_url": "http://scoot.net/gallery/pic.html?pic=372256&b=2009/06/rally9fromouterspace/Angelo/tinyindex.html",
    "photographer": "Angelo",
    "date_rally": "2009-06",
    "date_exif": null,
    "date_canonical": null,
    "date_source": "rally_slug",
    "r2_thumb": "https://pub-298bb0f2fc0a4462bd54d403b1bddbca.r2.dev/gallery/200906-Angelo/372256/thumb.jpg",
    "r2_full": null,
    "exif_meta": null
  },
  {
    "pic_id": "372257",
    "pic_url": "http://scoot.net/gallery/pic.html?pic=372257&b=2009/06/rally9fromouterspace/Angelo/tinyindex.html",
    "photographer": "Angelo",
    "date_rally": "2009-06",
    "date_exif": null,
    "date_canonical": null,
    "date_source": "rally_slug",
    "r2_thumb": "https://pub-298bb0f2fc0a4462bd54d403b1bddbca.r2.dev/gallery/200906-Angelo/372257/thumb.jpg",
    "r2_full": null,
    "exif_meta": null
  },
  {
    "pic_id": "372258",
    "pic_url": "http://scoot.net/gallery/pic.html?pic=372258&b=2009/06/rally9fromouterspace/Angelo/tinyindex.html",
    "photographer": "Angelo",
    "date_rally": "2009-06",
    "date_exif": null,
    "date_canonical": null,
    "date_source": "rally_slug",
    "r2_thumb": "https://pub-298bb0f2fc0a4462bd54d403b1bddbca.r2.dev/gallery/200906-Angelo/372258/thumb.jpg",
    "r2_full": null,
    "exif_meta": null
  },
  {
    "pic_id": "372259",
    "pic_url": "http://scoot.net/gallery/pic.html?pic=372259&b=2009/06/rally9fromouterspace/Angelo/tinyindex.html",
    "photographer": "Angelo",
    "date_rally": "2009-06",
    "date_exif": null,
    "date_canonical": null,
    "date_source": "rally_slug",
    "r2_thumb": "https://pub-298bb0f2fc0a4462bd54d403b1bddbca.r2.dev/gallery/200906-Angelo/372259/thumb.jpg",
    "r2_full": null,
    "exif_meta": null
  },
  {
    "pic_id": "372260",
    "pic_url": "http://scoot.net/gallery/pic.html?pic=372260&b=2009/06/rally9fromouterspace/Angelo/tinyindex.html",
    "photographer": "Angelo",
    "date_rally": "2009-06",
    "date_exif": null,
    "date_canonical": null,
    "date_source": "rally_slug",
    "r2_thumb": "https://pub-298bb0f2fc0a4462bd54d403b1bddbca.r2.dev/gallery/200906-Angelo/372260/thumb.jpg",
    "r2_full": null,
    "exif_meta": null
  },
  {
    "pic_id": "372261",
    "pic_url": "http://scoot.net/gallery/pic.html?pic=372261&b=2009/06/rally9fromouterspace/Angelo/tinyindex.html",
    "photographer": "Angelo",
    "date_rally": "2009-06",
    "date_exif": null,
    "date_canonical": null,
    "date_source": "rally_slug",
    "r2_thumb": "https://pub-298bb0f2fc0a4462bd54d403b1bddbca.r2.dev/gallery/200906-Angelo/372261/thumb.jpg",
    "r2_full": null,
    "exif_meta": null
  },
  {
    "pic_id": "375520",
    "pic_url": "http://scoot.net/gallery/pic.html?pic=375520&b=2009/06/rally9fromouterspace/Rick/tinyindex.html",
    "photographer": "Rick",
    "date_rally": "2009-06",
    "date_exif": "2009:06:12 21:44:26",
    "date_canonical": null,
    "date_source": "rally_slug",
    "r2_thumb": "https://pub-298bb0f2fc0a4462bd54d403b1bddbca.r2.dev/gallery/200906-Rick/375520/thumb.jpg",
    "r2_full": null,
    "exif_meta": {
      "DateTimeOriginal": "2009:06:12 21:44:26",
      "Make": "Canon",
      "Model": "Canon PowerShot A710 IS",
      "_warning": "Camera clock accuracy not guaranteed. Use date_canonical for trusted dates."
    }
  },
  {
    "pic_id": "375521",
    "pic_url": "http://scoot.net/gallery/pic.html?pic=375521&b=2009/06/rally9fromouterspace/Rick/tinyindex.html",
    "photographer": "Rick",
    "date_rally": "2009-06",
    "date_exif": "2009:06:12 21:44:33",
    "date_canonical": null,
    "date_source": "rally_slug",
    "r2_thumb": "https://pub-298bb0f2fc0a4462bd54d403b1bddbca.r2.dev/gallery/200906-Rick/375521/thumb.jpg",
    "r2_full": null,
    "exif_meta": {
      "DateTimeOriginal": "2009:06:12 21:44:33",
      "Make": "Canon",
      "Model": "Canon PowerShot A710 IS",
      "_warning": "Camera clock accuracy not guaranteed. Use date_canonical for trusted dates."
    }
  },
  {
    "pic_id": "375522",
    "pic_url": "http://scoot.net/gallery/pic.html?pic=375522&b=2009/06/rally9fromouterspace/Rick/tinyindex.html",
    "photographer": "Rick",
    "date_rally": "2009-06",
    "date_exif": "2009:06:12 21:44:45",
    "date_canonical": null,
    "date_source": "rally_slug",
    "r2_thumb": "https://pub-298bb0f2fc0a4462bd54d403b1bddbca.r2.dev/gallery/200906-Rick/375522/thumb.jpg",
    "r2_full": null,
    "exif_meta": {
      "DateTimeOriginal": "2009:06:12 21:44:45",
      "Make": "Canon",
      "Model": "Canon PowerShot A710 IS",
      "_warning": "Camera clock accuracy not guaranteed. Use date_canonical for trusted dates."
    }
  },
  {
    "pic_id": "375523",
    "pic_url": "http://scoot.net/gallery/pic.html?pic=375523&b=2009/06/rally9fromouterspace/Rick/tinyindex.html",
    "photographer": "Rick",
    "date_rally": "2009-06",
    "date_exif": "2009:06:12 21:44:55",
    "date_canonical": null,
    "date_source": "rally_slug",
    "r2_thumb": "https://pub-298bb0f2fc0a4462bd54d403b1bddbca.r2.dev/gallery/200906-Rick/375523/thumb.jpg",
    "r2_full": null,
    "exif_meta": {
      "DateTimeOriginal": "2009:06:12 21:44:55",
      "Make": "Canon",
      "Model": "Canon PowerShot A710 IS",
      "_warning": "Camera clock accuracy not guaranteed. Use date_canonical for trusted dates."
    }
  },
  {
    "pic_id": "375524",
    "pic_url": "http://scoot.net/gallery/pic.html?pic=375524&b=2009/06/rally9fromouterspace/Rick/tinyindex.html",
    "photographer": "Rick",
    "date_rally": "2009-06",
    "date_exif": "2009:06:12 21:45:08",
    "date_canonical": null,
    "date_source": "rally_slug",
    "r2_thumb": "https://pub-298bb0f2fc0a4462bd54d403b1bddbca.r2.dev/gallery/200906-Rick/375524/thumb.jpg",
    "r2_full": null,
    "exif_meta": {
      "DateTimeOriginal": "2009:06:12 21:45:08",
      "Make": "Canon",
      "Model": "Canon PowerShot A710 IS",
      "_warning": "Camera clock accuracy not guaranteed. Use date_canonical for trusted dates."
    }
  },
  {
    "pic_id": "375525",
    "pic_url": "http://scoot.net/gallery/pic.html?pic=375525&b=2009/06/rally9fromouterspace/Rick/tinyindex.html",
    "photographer": "Rick",
    "date_rally": "2009-06",
    "date_exif": "2009:06:12 21:45:16",
    "date_canonical": null,
    "date_source": "rally_slug",
    "r2_thumb": "https://pub-298bb0f2fc0a4462bd54d403b1bddbca.r2.dev/gallery/200906-Rick/375525/thumb.jpg",
    "r2_full": null,
    "exif_meta": {
      "DateTimeOriginal": "2009:06:12 21:45:16",
      "Make": "Canon",
      "Model": "Canon PowerShot A710 IS",
      "_warning": "Camera clock accuracy not guaranteed. Use date_canonical for trusted dates."
    }
  },
  {
    "pic_id": "375526",
    "pic_url": "http://scoot.net/gallery/pic.html?pic=375526&b=2009/06/rally9fromouterspace/Rick/tinyindex.html",
    "photographer": "Rick",
    "date_rally": "2009-06",
    "date_exif": "2009:06:12 21:45:34",
    "date_canonical": null,
    "date_source": "rally_slug",
    "r2_thumb": "https://pub-298bb0f2fc0a4462bd54d403b1bddbca.r2.dev/gallery/200906-Rick/375526/thumb.jpg",
    "r2_full": null,
    "exif_meta": {
      "DateTimeOriginal": "2009:06:12 21:45:34",
      "Make": "Canon",
      "Model": "Canon PowerShot A710 IS",
      "_warning": "Camera clock accuracy not guaranteed. Use date_canonical for trusted dates."
    }
  },
  {
    "pic_id": "375527",
    "pic_url": "http://scoot.net/gallery/pic.html?pic=375527&b=2009/06/rally9fromouterspace/Rick/tinyindex.html",
    "photographer": "Rick",
    "date_rally": "2009-06",
    "date_exif": "2009:06:12 21:45:43",
    "date_canonical": null,
    "date_source": "rally_slug",
    "r2_thumb": "https://pub-298bb0f2fc0a4462bd54d403b1bddbca.r2.dev/gallery/200906-Rick/375527/thumb.jpg",
    "r2_full": null,
    "exif_meta": {
      "DateTimeOriginal": "2009:06:12 21:45:43",
      "Make": "Canon",
      "Model": "Canon PowerShot A710 IS",
      "_warning": "Camera clock accuracy not guaranteed. Use date_canonical for trusted dates."
    }
  },
  {
    "pic_id": "375528",
    "pic_url": "http://scoot.net/gallery/pic.html?pic=375528&b=2009/06/rally9fromouterspace/Rick/tinyindex.html",
    "photographer": "Rick",
    "date_rally": "2009-06",
    "date_exif": "2009:06:12 21:45:56",
    "date_canonical": null,
    "date_source": "rally_slug",
    "r2_thumb": "https://pub-298bb0f2fc0a4462bd54d403b1bddbca.r2.dev/gallery/200906-Rick/375528/thumb.jpg",
    "r2_full": null,
    "exif_meta": {
      "DateTimeOriginal": "2009:06:12 21:45:56",
      "Make": "Canon",
      "Model": "Canon PowerShot A710 IS",
      "_warning": "Camera clock accuracy not guaranteed. Use date_canonical for trusted dates."
    }
  },
  {
    "pic_id": "375529",
    "pic_url": "http://scoot.net/gallery/pic.html?pic=375529&b=2009/06/rally9fromouterspace/Rick/tinyindex.html",
    "photographer": "Rick",
    "date_rally": "2009-06",
    "date_exif": "2009:06:12 21:46:06",
    "date_canonical": null,
    "date_source": "rally_slug",
    "r2_thumb": "https://pub-298bb0f2fc0a4462bd54d403b1bddbca.r2.dev/gallery/200906-Rick/375529/thumb.jpg",
    "r2_full": null,
    "exif_meta": {
      "DateTimeOriginal": "2009:06:12 21:46:06",
      "Make": "Canon",
      "Model": "Canon PowerShot A710 IS",
      "_warning": "Camera clock accuracy not guaranteed. Use date_canonical for trusted dates."
    }
  },
  {
    "pic_id": "375530",
    "pic_url": "http://scoot.net/gallery/pic.html?pic=375530&b=2009/06/rally9fromouterspace/Rick/tinyindex.html",
    "photographer": "Rick",
    "date_rally": "2009-06",
    "date_exif": "2009:06:12 21:46:14",
    "date_canonical": null,
    "date_source": "rally_slug",
    "r2_thumb": "https://pub-298bb0f2fc0a4462bd54d403b1bddbca.r2.dev/gallery/200906-Rick/375530/thumb.jpg",
    "r2_full": null,
    "exif_meta": {
      "DateTimeOriginal": "2009:06:12 21:46:14",
      "Make": "Canon",
      "Model": "Canon PowerShot A710 IS",
      "_warning": "Camera clock accuracy not guaranteed. Use date_canonical for trusted dates."
    }
  },
  {
    "pic_id": "375531",
    "pic_url": "http://scoot.net/gallery/pic.html?pic=375531&b=2009/06/rally9fromouterspace/Rick/tinyindex.html",
    "photographer": "Rick",
    "date_rally": "2009-06",
    "date_exif": "2009:06:23 05:43:14",
    "date_canonical": null,
    "date_source": "rally_slug",
    "r2_thumb": "https://pub-298bb0f2fc0a4462bd54d403b1bddbca.r2.dev/gallery/200906-Rick/375531/thumb.jpg",
    "r2_full": null,
    "exif_meta": {
      "DateTimeOriginal": "2009:06:23 05:43:14",
      "Make": "Canon",
      "Model": "Canon PowerShot A710 IS",
      "_warning": "Camera clock accuracy not guaranteed. Use date_canonical for trusted dates."
    }
  }
]